shl/__init__.py
shl/__main__.py
shl/main.py
shl/install_nn2/version
shl/install_nn2/c906/include/shl_debug.h
shl/install_nn2/c906/include/shl_memory.h
shl/install_nn2/c906/include/shl_multithread.h
shl/install_nn2/c906/include/shl_profiler.h
shl/install_nn2/c906/include/shl_utils.h
shl/install_nn2/c906/include/csinn/csi_nn.h
shl/install_nn2/c906/include/csinn/csinn_data_structure.h
shl/install_nn2/c906/include/csinn/csinn_runtime.h
shl/install_nn2/c906/include/graph/shl_gref.h
shl/install_nn2/c906/include/graph/shl_node.h
shl/install_nn2/c906/include/shl_public/shl_c906.h
shl/install_nn2/c906/include/shl_public/shl_c920.h
shl/install_nn2/c906/include/shl_public/shl_pnna.h
shl/install_nn2/c906/include/shl_public/shl_ref.h
shl/install_nn2/c906/include/shl_public/shl_tvmgen.h
shl/install_nn2/c906/lib/libshl.a
shl/install_nn2/c906/lib/libshl_c906.a
shl/install_nn2/c907/include/shl_debug.h
shl/install_nn2/c907/include/shl_memory.h
shl/install_nn2/c907/include/shl_multithread.h
shl/install_nn2/c907/include/shl_profiler.h
shl/install_nn2/c907/include/shl_utils.h
shl/install_nn2/c907/include/csinn/csi_nn.h
shl/install_nn2/c907/include/csinn/csinn_data_structure.h
shl/install_nn2/c907/include/csinn/csinn_runtime.h
shl/install_nn2/c907/include/graph/shl_gref.h
shl/install_nn2/c907/include/graph/shl_node.h
shl/install_nn2/c907/include/shl_public/shl_c906.h
shl/install_nn2/c907/include/shl_public/shl_c920.h
shl/install_nn2/c907/include/shl_public/shl_pnna.h
shl/install_nn2/c907/include/shl_public/shl_ref.h
shl/install_nn2/c907/include/shl_public/shl_tvmgen.h
shl/install_nn2/c907/lib/libshl.a
shl/install_nn2/c907/lib/libshl_c907.a
shl/install_nn2/c907_rv32/include/shl_debug.h
shl/install_nn2/c907_rv32/include/shl_memory.h
shl/install_nn2/c907_rv32/include/shl_multithread.h
shl/install_nn2/c907_rv32/include/shl_profiler.h
shl/install_nn2/c907_rv32/include/shl_utils.h
shl/install_nn2/c907_rv32/include/csinn/csi_nn.h
shl/install_nn2/c907_rv32/include/csinn/csinn_data_structure.h
shl_python-3.2.2.dist-info/METADATA
shl_python-3.2.2.dist-info/WHEEL
shl_python-3.2.2.dist-info/entry_points.txt
shl_python-3.2.2.dist-info/top_level.txt
shl_python-3.2.2.dist-info/RECORD
