Metadata-Version: 2.1
Name: shl-python
Version: 3.2.2
Summary: SHL: Structure of Heterogeneous Library from T-HEAD
Home-page: https://github.com/T-head-Semi/csi-nn2
Author: UNKNOWN
Author-email: UNKNOWN
License: UNKNOWN
Platform: UNKNOWN
